MANIFEST.in
setup.py
./pyzootool/__init__.py
./pyzootool/controller.py
./pyzootool/items.py
./pyzootool/users.py
pyzootool.egg-info/PKG-INFO
pyzootool.egg-info/SOURCES.txt
pyzootool.egg-info/dependency_links.txt
pyzootool.egg-info/requires.txt
pyzootool.egg-info/top_level.txt