Metadata-Version: 1.0
Name: pyzootool
Version: 0.2
Summary: A wrapper of the zootool.com API
Home-page: http://www.f4ntasmic.com
Author: Mark Rogers
Author-email: f4nt@f4ntasmic.com
License: UNKNOWN
Keywords: zootool socialmedia api
Platform: UNKNOWN
Classifier: Intended Audience :: Developers
Classifier: Programming Language :: Python
Classifier: License :: OSI Approved :: BSD License
